{"date":"11.05.2026 07:11","rows":[{"HFB":"06","Product Area":"0611","NR ART.":"00555250","NAZWA ART.":"TÄNNFORSEN sza lustr/drz 100x15x95 biały","SM":"2","SRP":"1","BoH":0,"BoH LD":1,"Status":"Art. niedostepny","Zmiana ceny":false,"Price1":1299,"Price1 LD":1299,"Loc Price":0,"LocPrice LD":0,"Zmiana lokalizacji":false,"Lokalizacja":"733105","LOK LD":"733105","FPRICE1":0,"FPRICE LD":0,"Notatki":"OK.","EDS":"","Fireclass":"NFR","SMDQ":"-"},{"HFB":"14","Product Area":"1413","NR ART.":"10619020","NAZWA ART.":"HAVSTULPAN patel d pizz 35 żeliwo","SM":"0","SRP":"1","BoH":0,"BoH LD":2,"Status":"Art. niedostepny","Zmiana ceny":false,"Price1":99.99,"Price1 LD":99.99,"Loc Price":0,"LocPrice LD":0,"Zmiana lokalizacji":false,"Lokalizacja":"M14H21","LOK LD":"M14H21","FPRICE1":0,"FPRICE LD":0,"Notatki":"OK.","EDS":"","Fireclass":"SFR","SMDQ":"-"},{"HFB":"02","Product Area":"0211","NR ART.":"20584732","NAZWA ART.":"LÅDMAKARE wkł przegr 76x34x24 imit. dębu","SM":"2","SRP":"1","BoH":0,"BoH LD":6,"Status":"Art. niedostepny","Zmiana ceny":false,"Price1":85,"Price1 LD":85,"Loc Price":0,"LocPrice LD":0,"Zmiana lokalizacji":false,"Lokalizacja":"820910","LOK LD":"820910","FPRICE1":0,"FPRICE LD":0,"Notatki":"OK.","EDS":"","Fireclass":"NFR","SMDQ":"-"},{"HFB":"10","Product Area":"1043","NR ART.":"60528584","NAZWA ART.":"MITTLED list ośw LED do bl kuch 60 przyciem b EU","SM":"2","SRP":"1","BoH":0,"BoH LD":1,"Status":"Art. niedostepny","Zmiana ceny":false,"Price1":65,"Price1 LD":65,"Loc Price":0,"LocPrice LD":0,"Zmiana lokalizacji":false,"Lokalizacja":"712510","LOK LD":"712510","FPRICE1":0,"FPRICE LD":0,"Notatki":"OK.","EDS":"","Fireclass":"NFR","SMDQ":"-"},{"HFB":"10","Product Area":"1081","NR ART.":"60615029","NAZWA ART.":"SOLVINDEN 2026 lam wisz słon LED 45 zew/kula b","SM":"0","SRP":"1","BoH":0,"BoH LD":7,"Status":"Art. niedostepny","Zmiana ceny":false,"Price1":29.99,"Price1 LD":29.99,"Loc Price":0,"LocPrice LD":0,"Zmiana lokalizacji":false,"Lokalizacja":"M10D09","LOK LD":"M10D09","FPRICE1":0,"FPRICE LD":0,"Notatki":"OK.","EDS":46296,"Fireclass":"NFR","SMDQ":"-"},{"HFB":"11","Product Area":"1133","NR ART.":"60623166","NAZWA ART.":"STAVBJÖRNBÄR zasł pryszn 180x200 czarny/biały","SM":"0","SRP":"1","BoH":0,"BoH LD":1,"Status":"Art. niedostepny","Zmiana ceny":false,"Price1":59.99,"Price1 LD":59.99,"Loc Price":0,"LocPrice LD":0,"Zmiana lokalizacji":false,"Lokalizacja":"M06O13","LOK LD":"M06O13","FPRICE1":0,"FPRICE LD":0,"Notatki":"OK.","EDS":"","Fireclass":"NFR","SMDQ":"-"},{"HFB":"18","Product Area":"1841","NR ART.":"00449636","NAZWA ART.":"NYDALA uchw 154 mm czarny 2szt.","SM":"1","SRP":"7","BoH":1,"BoH LD":0,"Status":"Art. dostepny","Zmiana ceny":false,"Price1":30,"Price1 LD":30,"Loc Price":0,"LocPrice LD":0,"Zmiana lokalizacji":false,"Lokalizacja":"","LOK LD":0,"FPRICE1":0,"FPRICE LD":0,"Notatki":"Usun info o niedostepnosci artykulu.","EDS":46113,"Fireclass":"NFR","SMDQ":"-"},{"HFB":"10","Product Area":"1081","NR ART.":"00615008","NAZWA ART.":"SOLVINDEN 2026 lam wisz słon LED 30 zew/kula b","SM":"0","SRP":"1","BoH":-1,"BoH LD":1,"Status":"Art. niedostepny","Zmiana ceny":false,"Price1":24.99,"Price1 LD":24.99,"Loc Price":0,"LocPrice LD":0,"Zmiana lokalizacji":false,"Lokalizacja":"M10D09","LOK LD":"M10D09","FPRICE1":0,"FPRICE LD":0,"Notatki":"Wstaw info \u0027Artykul chwilowo niedostepny\u0027.","EDS":46296,"Fireclass":"NFR","SMDQ":"-"},{"HFB":"01","Product Area":"0126","NR ART.":"20565521","NAZWA ART.":"KJUGE puf ze schow KNISA średnioniebieski","SM":"1","SRP":"1","BoH":1,"BoH LD":-1,"Status":"Art. dostepny","Zmiana ceny":false,"Price1":39,"Price1 LD":39,"Loc Price":0,"LocPrice LD":0,"Zmiana lokalizacji":false,"Lokalizacja":"064410","LOK LD":"064410","FPRICE1":0,"FPRICE LD":0,"Notatki":"Usun info o niedostepnosci artykulu.","EDS":46204,"Fireclass":"NFR","SMDQ":"-"},{"HFB":"07","Product Area":"0782","NR ART.":"30601689","NAZWA ART.":"KLAVRESTRÖM polka scienna 60x20 dąb","SM":"1","SRP":"1","BoH":0,"BoH LD":12,"Status":"Art. niedostepny","Zmiana ceny":false,"Price1":149,"Price1 LD":149,"Loc Price":0,"LocPrice LD":0,"Zmiana lokalizacji":false,"Lokalizacja":"132010","LOK LD":"132010","FPRICE1":0,"FPRICE LD":0,"Notatki":"OK.","EDS":"","Fireclass":"NFR","SMDQ":"-"},{"HFB":"11","Product Area":"1111","NR ART.":"50356564","NAZWA ART.":"DVALA N przśc/g 180x200 biały","SM":"0","SRP":"7","BoH":1,"BoH LD":0,"Status":"Art. dostepny","Zmiana ceny":false,"Price1":59.99,"Price1 LD":59.99,"Loc Price":0,"LocPrice LD":0,"Zmiana lokalizacji":false,"Lokalizacja":"M11L15","LOK LD":"M11L15","FPRICE1":0,"FPRICE LD":0,"Notatki":"Usun info o niedostepnosci artykulu.","EDS":46023,"Fireclass":"NFR","SMDQ":"-"},{"HFB":"11","Product Area":"1111","NR ART.":"50549643","NAZWA ART.":"DVALA przśc/g 90x200 szarozielony","SM":"0","SRP":"1","BoH":362,"BoH LD":386,"Status":false,"Zmiana ceny":false,"Price1":29.99,"Price1 LD":29.99,"Loc Price":0,"LocPrice LD":0,"Zmiana lokalizacji":"M11L13","Lokalizacja":"M11L13","LOK LD":"M11J15","FPRICE1":0,"FPRICE LD":0,"Notatki":"OK.","EDS":46204,"Fireclass":"NFR","SMDQ":"-"},{"HFB":"08","Product Area":"0824","NR ART.":"70594026","NAZWA ART.":"TONSTAD rama krzesła kremowy","SM":"1","SRP":"1","BoH":-1,"BoH LD":4,"Status":"Art. niedostepny","Zmiana ceny":false,"Price1":249,"Price1 LD":249,"Loc Price":0,"LocPrice LD":0,"Zmiana lokalizacji":false,"Lokalizacja":"082910","LOK LD":"082910","FPRICE1":0,"FPRICE LD":0,"Notatki":"Wstaw info \u0027Artykul chwilowo niedostepny\u0027.","EDS":"","Fireclass":"NFR","SMDQ":"-"},{"HFB":"12","Product Area":"1231","NR ART.":"80617490","NAZWA ART.":"IKEA PS 2026 posz 50x50 biały/wielobarwny RECY","SM":"0","SRP":"1","BoH":22,"BoH LD":22,"Status":false,"Zmiana ceny":false,"Price1":19.99,"Price1 LD":19.99,"Loc Price":0,"LocPrice LD":0,"Zmiana lokalizacji":"CO1000","Lokalizacja":"CO1000","LOK LD":0,"FPRICE1":0,"FPRICE LD":0,"Notatki":"OK.","EDS":"","Fireclass":"NFR","SMDQ":"-"},{"HFB":"12","Product Area":"1211","NR ART.":"90548972","NAZWA ART.":"SANDDÅDRA fir 2 145x300 na tunelu/biały","SM":"0","SRP":"7","BoH":0,"BoH LD":1,"Status":"Art. niedostepny","Zmiana ceny":false,"Price1":99.99,"Price1 LD":99.99,"Loc Price":0,"LocPrice LD":0,"Zmiana lokalizacji":false,"Lokalizacja":"M12A12","LOK LD":"M12A12","FPRICE1":0,"FPRICE LD":0,"Notatki":"OK.","EDS":46023,"Fireclass":"NFR","SMDQ":"-"},{"HFB":"02","Product Area":"0211","NR ART.":"90584724","NAZWA ART.":"LÅDMAKARE panel środ 35x212 imit. dębu","SM":"2","SRP":"1","BoH":0,"BoH LD":3,"Status":"Art. niedostepny","Zmiana ceny":false,"Price1":85,"Price1 LD":85,"Loc Price":0,"LocPrice LD":0,"Zmiana lokalizacji":false,"Lokalizacja":"642510","LOK LD":"642510","FPRICE1":0,"FPRICE LD":0,"Notatki":"OK.","EDS":"","Fireclass":"NFR","SMDQ":"-"},{"HFB":"70","Product Area":"7015","NR ART.":"90609116","NAZWA ART.":"MÅNGSBO wbud okap kom 60 IKEA 700","SM":"2","SRP":"1","BoH":0,"BoH LD":0,"Status":false,"Zmiana ceny":false,"Price1":1299,"Price1 LD":1299,"Loc Price":0,"LocPrice LD":0,"Zmiana lokalizacji":"700600","Lokalizacja":"700600","LOK LD":0,"FPRICE1":0,"FPRICE LD":0,"Notatki":"OK.","EDS":"","Fireclass":"NFR","SMDQ":"-"},{"HFB":"15","Product Area":"1541","NR ART.":"90611906","NAZWA ART.":"FANTASTISK N serwetki 33x33 jasnozielony 50szt.","SM":"0","SRP":"1","BoH":1,"BoH LD":0,"Status":"Art. dostepny","Zmiana ceny":false,"Price1":6.99,"Price1 LD":6.99,"Loc Price":0,"LocPrice LD":0,"Zmiana lokalizacji":false,"Lokalizacja":"M15B14","LOK LD":"M15B14","FPRICE1":0,"FPRICE LD":0,"Notatki":"Usun info o niedostepnosci artykulu.","EDS":46204,"Fireclass":"NFR","SMDQ":"-"},{"HFB":"16","Product Area":"1621","NR ART.":"90612029","NAZWA ART.":"STJÄRNANIS 2026 skrz kwiat 75x27 zew akc","SM":"0","SRP":"1","BoH":-1,"BoH LD":2,"Status":"Art. niedostepny","Zmiana ceny":false,"Price1":149,"Price1 LD":149,"Loc Price":0,"LocPrice LD":0,"Zmiana lokalizacji":false,"Lokalizacja":"M16T01","LOK LD":"M16T01","FPRICE1":0,"FPRICE LD":0,"Notatki":"Wstaw info \u0027Artykul chwilowo niedostepny\u0027.","EDS":46204,"Fireclass":"NFR","SMDQ":"-"},{"HFB":"11","Product Area":"1111","NR ART.":"10345346","NAZWA ART.":"ULLVIDE przśc/g 120x200 biały","SM":"0","SRP":"1","BoH":0,"BoH LD":4,"Status":"Art. niedostepny","Zmiana ceny":false,"Price1":54.99,"Price1 LD":54.99,"Loc Price":0,"LocPrice LD":0,"Zmiana lokalizacji":false,"Lokalizacja":"M11L13","LOK LD":"M11L13","FPRICE1":0,"FPRICE LD":0,"Notatki":"OK.","EDS":"","Fireclass":"NFR","SMDQ":"-"},{"HFB":"16","Product Area":"1623","NR ART.":"40610607","NAZWA ART.":"FEJKA szt rośl donicz 21 w/z/bambus","SM":"0","SRP":"1","BoH":-2,"BoH LD":7,"Status":"Art. niedostepny","Zmiana ceny":false,"Price1":199,"Price1 LD":199,"Loc Price":0,"LocPrice LD":0,"Zmiana lokalizacji":false,"Lokalizacja":"M16N01","LOK LD":"M16N01","FPRICE1":0,"FPRICE LD":0,"Notatki":"Wstaw info \u0027Artykul chwilowo niedostepny\u0027.","EDS":"","Fireclass":"NFR","SMDQ":"-"},{"HFB":"10","Product Area":"1012","NR ART.":"50608557","NAZWA ART.":"IKEA PS 2026 przen lam LED 22 btr przyciem/zie jr","SM":"0","SRP":"1","BoH":162,"BoH LD":162,"Status":false,"Zmiana ceny":false,"Price1":99.99,"Price1 LD":99.99,"Loc Price":0,"LocPrice LD":0,"Zmiana lokalizacji":"CO1000","Lokalizacja":"CO1000","LOK LD":0,"FPRICE1":0,"FPRICE LD":0,"Notatki":"OK.","EDS":"","Fireclass":"NFR","SMDQ":"-"},{"HFB":"15","Product Area":"1531","NR ART.":"50619867","NAZWA ART.":"SOLUPPGÅNG sztućce sałat 2s bambus","SM":"0","SRP":"1","BoH":0,"BoH LD":2,"Status":"Art. niedostepny","Zmiana ceny":false,"Price1":19.99,"Price1 LD":19.99,"Loc Price":0,"LocPrice LD":0,"Zmiana lokalizacji":false,"Lokalizacja":"M15G21","LOK LD":"M15G21","FPRICE1":0,"FPRICE LD":0,"Notatki":"OK.","EDS":46204,"Fireclass":"NFR","SMDQ":"-"},{"HFB":"06","Product Area":"0612","NR ART.":"60574905","NAZWA ART.":"FRÖSJÖN reg nad toal 65x156 czarny","SM":"2","SRP":"1","BoH":0,"BoH LD":1,"Status":"Art. niedostepny","Zmiana ceny":false,"Price1":199,"Price1 LD":199,"Loc Price":0,"LocPrice LD":0,"Zmiana lokalizacji":false,"Lokalizacja":"781210","LOK LD":"781210","FPRICE1":0,"FPRICE LD":0,"Notatki":"OK.","EDS":"","Fireclass":"NFR","SMDQ":"-"},{"HFB":"17","Product Area":"1714","NR ART.":"10411440","NAZWA ART.":"TOSTERÖ skrz przechow ogr 129x44x79 czarny","SM":"1","SRP":"1","BoH":0,"BoH LD":4,"Status":"Art. niedostepny","Zmiana ceny":false,"Price1":179,"Price1 LD":179,"Loc Price":0,"LocPrice LD":0,"Zmiana lokalizacji":false,"Lokalizacja":"191110","LOK LD":"191110","FPRICE1":0,"FPRICE LD":0,"Notatki":"OK.","EDS":"","Fireclass":"NFR","SMDQ":"-"},{"HFB":"03","Product Area":"0352","NR ART.":"20485242","NAZWA ART.":"FJÄLLBERGET krz kon z kółk okldb bjcb/GUNNARED bż","SM":"2","SRP":"1","BoH":0,"BoH LD":1,"Status":"Art. niedostepny","Zmiana ceny":false,"Price1":799,"Price1 LD":799,"Loc Price":0,"LocPrice LD":0,"Zmiana lokalizacji":false,"Lokalizacja":"771110","LOK LD":"771110","FPRICE1":0,"FPRICE LD":0,"Notatki":"OK.","EDS":46388,"Fireclass":"NFR","SMDQ":"-"},{"HFB":"09","Product Area":"0922","NR ART.":"20560613","NAZWA ART.":"BARNDRÖM pudełko 26x37x17 beżowy","SM":"0","SRP":"1","BoH":-1,"BoH LD":6,"Status":"Art. niedostepny","Zmiana ceny":false,"Price1":29.99,"Price1 LD":29.99,"Loc Price":0,"LocPrice LD":0,"Zmiana lokalizacji":false,"Lokalizacja":"S09P15","LOK LD":"S09P15","FPRICE1":0,"FPRICE LD":0,"Notatki":"Wstaw info \u0027Artykul chwilowo niedostepny\u0027.","EDS":"","Fireclass":"NFR","SMDQ":"-"},{"HFB":"17","Product Area":"1721","NR ART.":"20600464","NAZWA ART.":"STRANDÖN osł wiatr/słońce jk pom/jkż","SM":"1","SRP":"1","BoH":0,"BoH LD":0,"Status":false,"Zmiana ceny":false,"Price1":99.99,"Price1 LD":99.99,"Loc Price":0,"LocPrice LD":0,"Zmiana lokalizacji":0,"Lokalizacja":"","LOK LD":"190610","FPRICE1":0,"FPRICE LD":0,"Notatki":"OK.","EDS":46204,"Fireclass":"NFR","SMDQ":"-"},{"HFB":"04","Product Area":"0422","NR ART.":"30446467","NAZWA ART.":"KOMPL drazek 100x35 idbjb","SM":"1","SRP":"1","BoH":0,"BoH LD":5,"Status":"Art. niedostepny","Zmiana ceny":false,"Price1":70,"Price1 LD":70,"Loc Price":0,"LocPrice LD":0,"Zmiana lokalizacji":false,"Lokalizacja":"264905","LOK LD":"264905","FPRICE1":0,"FPRICE LD":0,"Notatki":"OK.","EDS":"","Fireclass":"NFR","SMDQ":"-"},{"HFB":"10","Product Area":"1012","NR ART.":"40608548","NAZWA ART.":"IKEA PS 2026 przen lam LED 22 btr przyciem/cze jn","SM":"0","SRP":"1","BoH":162,"BoH LD":162,"Status":false,"Zmiana ceny":false,"Price1":99.99,"Price1 LD":99.99,"Loc Price":0,"LocPrice LD":0,"Zmiana lokalizacji":"CO1000","Lokalizacja":"CO1000","LOK LD":0,"FPRICE1":0,"FPRICE LD":0,"Notatki":"OK.","EDS":"","Fireclass":"NFR","SMDQ":"-"},{"HFB":"14","Product Area":"1434","NR ART.":"40618571","NAZWA ART.":"NÅLBLECKA półka nar met/bamb d bla kuch","SM":"0","SRP":"1","BoH":0,"BoH LD":11,"Status":"Art. niedostepny","Zmiana ceny":false,"Price1":59.99,"Price1 LD":59.99,"Loc Price":0,"LocPrice LD":0,"Zmiana lokalizacji":false,"Lokalizacja":"M14I16","LOK LD":"M14I16","FPRICE1":0,"FPRICE LD":0,"Notatki":"OK.","EDS":"","Fireclass":"NFR","SMDQ":"-"},{"HFB":"09","Product Area":"0962","NR ART.":"50457600","NAZWA ART.":"LENAST N przść dz 60x120 w kropki/Księżyc 2szt.","SM":"0","SRP":"1","BoH":0,"BoH LD":2,"Status":"Art. niedostepny","Zmiana ceny":false,"Price1":59.99,"Price1 LD":59.99,"Loc Price":0,"LocPrice LD":0,"Zmiana lokalizacji":false,"Lokalizacja":"S09O12","LOK LD":"S09O12","FPRICE1":0,"FPRICE LD":0,"Notatki":"OK.","EDS":46204,"Fireclass":"NFR","SMDQ":"-"},{"HFB":"07","Product Area":"0721","NR ART.":"50595178","NAZWA ART.":"SINARP drz 60x80 okl dęb","SM":"2","SRP":"1","BoH":4,"BoH LD":0,"Status":"Art. dostepny","Zmiana ceny":false,"Price1":275,"Price1 LD":275,"Loc Price":0,"LocPrice LD":0,"Zmiana lokalizacji":false,"Lokalizacja":"694202","LOK LD":"694202","FPRICE1":0,"FPRICE LD":0,"Notatki":"Usun info o niedostepnosci artykulu.","EDS":"","Fireclass":"NFR","SMDQ":"-"},{"HFB":"04","Product Area":"0421","NR ART.":"50596489","NAZWA ART.":"LASTARE nadst z drz 40x42x36 biały","SM":"1","SRP":"1","BoH":6,"BoH LD":0,"Status":"Art. dostepny","Zmiana ceny":false,"Price1":100,"Price1 LD":100,"Loc Price":0,"LocPrice LD":0,"Zmiana lokalizacji":false,"Lokalizacja":"106910","LOK LD":"106910","FPRICE1":0,"FPRICE LD":0,"Notatki":"Usun info o niedostepnosci artykulu.","EDS":"","Fireclass":"NFR","SMDQ":"-"},{"HFB":"10","Product Area":"1021","NR ART.":"50598214","NAZWA ART.":"VÄSTMÄRKE ład bezprz z lmp","SM":"0","SRP":"1","BoH":0,"BoH LD":1,"Status":"Art. niedostepny","Zmiana ceny":false,"Price1":99.99,"Price1 LD":99.99,"Loc Price":0,"LocPrice LD":0,"Zmiana lokalizacji":false,"Lokalizacja":"M10G08","LOK LD":"M10G08","FPRICE1":0,"FPRICE LD":0,"Notatki":"OK.","EDS":"","Fireclass":"NFR","SMDQ":"-"},{"HFB":"04","Product Area":"0433","NR ART.":"70182191","NAZWA ART.":"RISÖR śc dział 216x185 biały/czarny","SM":"2","SRP":"1","BoH":0,"BoH LD":1,"Status":"Art. niedostepny","Zmiana ceny":false,"Price1":699,"Price1 LD":699,"Loc Price":0,"LocPrice LD":0,"Zmiana lokalizacji":false,"Lokalizacja":"641710","LOK LD":"641710","FPRICE1":0,"FPRICE LD":0,"Notatki":"OK.","EDS":"","Fireclass":"NFR","SMDQ":"-"},{"HFB":"16","Product Area":"1633","NR ART.":"90542178","NAZWA ART.":"SMÄLLSPIREA wazon 17 szkło bezbarwne/wzór","SM":"0","SRP":"1","BoH":66,"BoH LD":67,"Status":false,"Zmiana ceny":false,"Price1":19.99,"Price1 LD":19.99,"Loc Price":0,"LocPrice LD":0,"Zmiana lokalizacji":"M16M04","Lokalizacja":"M16M04","LOK LD":"M16M03","FPRICE1":0,"FPRICE LD":0,"Notatki":"OK.","EDS":46296,"Fireclass":"NFR","SMDQ":"-"},{"HFB":"01","Product Area":"0113","NR ART.":"90547623","NAZWA ART.":"VRETSTORP pokr sof rozkł 3o KARLSHOV beż/wielokol","SM":"2","SRP":"1","BoH":0,"BoH LD":1,"Status":"Art. niedostepny","Zmiana ceny":false,"Price1":999,"Price1 LD":999,"Loc Price":0,"LocPrice LD":0,"Zmiana lokalizacji":false,"Lokalizacja":"682927","LOK LD":"682927","FPRICE1":0,"FPRICE LD":0,"Notatki":"OK.","EDS":"","Fireclass":"NFR","SMDQ":"-"},{"HFB":"15","Product Area":"1551","NR ART.":"90612109","NAZWA ART.":"SMÖRFISK kubek 34 cl jasnozielony/różowy 2szt.","SM":"0","SRP":"1","BoH":0,"BoH LD":1,"Status":"Art. niedostepny","Zmiana ceny":false,"Price1":39.99,"Price1 LD":39.99,"Loc Price":0,"LocPrice LD":0,"Zmiana lokalizacji":false,"Lokalizacja":"M15A18","LOK LD":"M15A18","FPRICE1":0,"FPRICE LD":0,"Notatki":"OK.","EDS":46204,"Fireclass":"NFR","SMDQ":"-"},{"HFB":"06","Product Area":"0631","NR ART.":"10532084","NAZWA ART.":"BROGRUND N bat umyw, wys chrom","SM":"0","SRP":"1","BoH":0,"BoH LD":1,"Status":"Art. niedostepny","Zmiana ceny":false,"Price1":450,"Price1 LD":450,"Loc Price":0,"LocPrice LD":0,"Zmiana lokalizacji":false,"Lokalizacja":"M06T12","LOK LD":"M06T12","FPRICE1":0,"FPRICE LD":0,"Notatki":"OK.","EDS":46296,"Fireclass":"NFR","SMDQ":"-"},{"HFB":"07","Product Area":"0721","NR ART.":"10595175","NAZWA ART.":"SINARP drz 60x40 okl dęb","SM":"2","SRP":"1","BoH":0,"BoH LD":1,"Status":"Art. niedostepny","Zmiana ceny":false,"Price1":155,"Price1 LD":155,"Loc Price":0,"LocPrice LD":0,"Zmiana lokalizacji":false,"Lokalizacja":"694001","LOK LD":"694001","FPRICE1":0,"FPRICE LD":0,"Notatki":"OK.","EDS":"","Fireclass":"NFR","SMDQ":"-"},{"HFB":"16","Product Area":"1634","NR ART.":"10614975","NAZWA ART.":"GULDSPETT szt kwi 55 papier/eustoma biały","SM":"0","SRP":"1","BoH":-1,"BoH LD":1,"Status":"Art. niedostepny","Zmiana ceny":false,"Price1":12.99,"Price1 LD":12.99,"Loc Price":0,"LocPrice LD":0,"Zmiana lokalizacji":false,"Lokalizacja":"M16N03","LOK LD":"M16N03","FPRICE1":0,"FPRICE LD":0,"Notatki":"Wstaw info \u0027Artykul chwilowo niedostepny\u0027.","EDS":"","Fireclass":"NFR","SMDQ":"-"},{"HFB":"06","Product Area":"0623","NR ART.":"20605471","NAZWA ART.":"GANSJÖN kosz/odp 3 l czarny","SM":"0","SRP":"1","BoH":-1,"BoH LD":5,"Status":"Art. niedostepny","Zmiana ceny":false,"Price1":49.99,"Price1 LD":49.99,"Loc Price":0,"LocPrice LD":0,"Zmiana lokalizacji":false,"Lokalizacja":"M06R13","LOK LD":"M06R13","FPRICE1":0,"FPRICE LD":0,"Notatki":"Wstaw info \u0027Artykul chwilowo niedostepny\u0027.","EDS":"","Fireclass":"NFR","SMDQ":"-"},{"HFB":"10","Product Area":"1012","NR ART.":"30613569","NAZWA ART.":"IKEA PS 2026 przen lam LED 22 btr przyciem/n jż","SM":"0","SRP":"1","BoH":162,"BoH LD":162,"Status":false,"Zmiana ceny":false,"Price1":99.99,"Price1 LD":99.99,"Loc Price":0,"LocPrice LD":0,"Zmiana lokalizacji":"CO1000","Lokalizacja":"CO1000","LOK LD":0,"FPRICE1":0,"FPRICE LD":0,"Notatki":"OK.","EDS":"","Fireclass":"NFR","SMDQ":"-"},{"HFB":"16","Product Area":"1621","NR ART.":"40601009","NAZWA ART.":"MÄVINN wisz uchw na donicz biały/wykonano ręcznie","SM":"0","SRP":"1","BoH":0,"BoH LD":1,"Status":"Art. niedostepny","Zmiana ceny":false,"Price1":19.99,"Price1 LD":19.99,"Loc Price":0,"LocPrice LD":0,"Zmiana lokalizacji":false,"Lokalizacja":"M16T01","LOK LD":"M16T01","FPRICE1":0,"FPRICE LD":0,"Notatki":"OK.","EDS":46204,"Fireclass":"NFR","SMDQ":"-"},{"HFB":"07","Product Area":"0761","NR ART.":"50549836","NAZWA ART.":"UPPDATERA mata szuflady 50x48 szary","SM":"0","SRP":"1","BoH":0,"BoH LD":10,"Status":"Art. niedostepny","Zmiana ceny":false,"Price1":24.99,"Price1 LD":24.99,"Loc Price":0,"LocPrice LD":0,"Zmiana lokalizacji":false,"Lokalizacja":"S07C07","LOK LD":"S07C07","FPRICE1":0,"FPRICE LD":0,"Notatki":"OK.","EDS":"","Fireclass":"NFR","SMDQ":"-"},{"HFB":"06","Product Area":"0622","NR ART.":"70453998","NAZWA ART.":"KROKFJORDEN wiesz przyss ocynkowany","SM":"0","SRP":"1","BoH":1,"BoH LD":0,"Status":"Art. dostepny","Zmiana ceny":false,"Price1":29.99,"Price1 LD":29.99,"Loc Price":0,"LocPrice LD":0,"Zmiana lokalizacji":false,"Lokalizacja":"M06O12","LOK LD":"M06O12","FPRICE1":0,"FPRICE LD":0,"Notatki":"Usun info o niedostepnosci artykulu.","EDS":"","Fireclass":"NFR","SMDQ":"-"},{"HFB":"18","Product Area":"1831","NR ART.":"80399996","NAZWA ART.":"SKUBB pokr ubr 3s ciemnoszary","SM":"0","SRP":"1","BoH":0,"BoH LD":11,"Status":"Art. niedostepny","Zmiana ceny":false,"Price1":34.99,"Price1 LD":34.99,"Loc Price":0,"LocPrice LD":0,"Zmiana lokalizacji":false,"Lokalizacja":"M18K09","LOK LD":"M18K09","FPRICE1":0,"FPRICE LD":0,"Notatki":"OK.","EDS":"","Fireclass":"HFR","SMDQ":"-"},{"HFB":"01","Product Area":"0111","NR ART.":"80607641","NAZWA ART.":"SALTSJÖBADEN pokr so3 os TONERUD szary","SM":"2","SRP":"1","BoH":0,"BoH LD":2,"Status":"Art. niedostepny","Zmiana ceny":false,"Price1":499,"Price1 LD":499,"Loc Price":0,"LocPrice LD":0,"Zmiana lokalizacji":false,"Lokalizacja":"631610","LOK LD":"631610","FPRICE1":0,"FPRICE LD":0,"Notatki":"OK.","EDS":"","Fireclass":"NFR","SMDQ":"-"},{"HFB":"09","Product Area":"0974","NR ART.":"10573654","NAZWA ART.":"GULDVÄVARE ozd wielobarwny","SM":"0","SRP":"1","BoH":0,"BoH LD":4,"Status":"Art. niedostepny","Zmiana ceny":false,"Price1":49.99,"Price1 LD":49.99,"Loc Price":0,"LocPrice LD":0,"Zmiana lokalizacji":false,"Lokalizacja":"S09N12","LOK LD":"S09N12","FPRICE1":0,"FPRICE LD":0,"Notatki":"OK.","EDS":"","Fireclass":"NFR","SMDQ":"-"},{"HFB":"06","Product Area":"0623","NR ART.":"10581550","NAZWA ART.":"BROFJÄRDEN szczotka toal efekt chromowania","SM":"0","SRP":"1","BoH":0,"BoH LD":2,"Status":"Art. niedostepny","Zmiana ceny":false,"Price1":49.99,"Price1 LD":49.99,"Loc Price":0,"LocPrice LD":0,"Zmiana lokalizacji":false,"Lokalizacja":"M06R13","LOK LD":"M06R13","FPRICE1":0,"FPRICE LD":0,"Notatki":"OK.","EDS":"","Fireclass":"NFR","SMDQ":"-"},{"HFB":"12","Product Area":"1213","NR ART.":"10616328","NAZWA ART.":"VECKLARFLY zaluzje 80x155 bambus","SM":"0","SRP":"1","BoH":0,"BoH LD":2,"Status":"Art. niedostepny","Zmiana ceny":false,"Price1":329,"Price1 LD":329,"Loc Price":0,"LocPrice LD":0,"Zmiana lokalizacji":false,"Lokalizacja":"M12G10","LOK LD":"M12G10","FPRICE1":0,"FPRICE LD":0,"Notatki":"OK.","EDS":"","Fireclass":"NFR","SMDQ":"-"},{"HFB":"03","Product Area":"0371","NR ART.":"30586325","NAZWA ART.":"LÖPARBANA krz gamingowe VISSLE zielony","SM":"2","SRP":"1","BoH":3,"BoH LD":3,"Status":false,"Zmiana ceny":false,"Price1":399,"Price1 LD":399,"Loc Price":0,"LocPrice LD":0,"Zmiana lokalizacji":"812220","Lokalizacja":"812220","LOK LD":"802700","FPRICE1":199,"FPRICE LD":199,"Notatki":"OK.","EDS":"","Fireclass":"NFR","SMDQ":"-"},{"HFB":"09","Product Area":"0964","NR ART.":"30622856","NAZWA ART.":"BARNDRÖM N prześci gu/łóż rozsu 80x165 r 1szt RECY","SM":"0","SRP":"1","BoH":-1,"BoH LD":11,"Status":"Art. niedostepny","Zmiana ceny":false,"Price1":39.99,"Price1 LD":39.99,"Loc Price":0,"LocPrice LD":0,"Zmiana lokalizacji":false,"Lokalizacja":"S09O16","LOK LD":"S09O16","FPRICE1":0,"FPRICE LD":0,"Notatki":"Wstaw info \u0027Artykul chwilowo niedostepny\u0027.","EDS":"","Fireclass":"NFR","SMDQ":"-"},{"HFB":"11","Product Area":"1113","NR ART.":"50600387","NAZWA ART.":"PELARTUJA narz 150x250 czerwonobrązowy/beżowy RECY","SM":"0","SRP":"1","BoH":0,"BoH LD":1,"Status":"Art. niedostepny","Zmiana ceny":false,"Price1":99.99,"Price1 LD":99.99,"Loc Price":0,"LocPrice LD":0,"Zmiana lokalizacji":false,"Lokalizacja":"M12E12","LOK LD":"M12E12","FPRICE1":0,"FPRICE LD":0,"Notatki":"OK.","EDS":"","Fireclass":"NFR","SMDQ":"-"},{"HFB":"04","Product Area":"0422","NR ART.":"60446545","NAZWA ART.":"KOMPL N wys wiesz spod 100x35 biały","SM":"1","SRP":"1","BoH":0,"BoH LD":1,"Status":"Art. niedostepny","Zmiana ceny":false,"Price1":170,"Price1 LD":170,"Loc Price":0,"LocPrice LD":0,"Zmiana lokalizacji":false,"Lokalizacja":"225915","LOK LD":"225915","FPRICE1":0,"FPRICE LD":0,"Notatki":"OK.","EDS":46296,"Fireclass":"NFR","SMDQ":"-"},{"HFB":"16","Product Area":"1623","NR ART.":"70617693","NAZWA ART.":"FEJKA szt rośl donicz 12 w/z/lawenda lil","SM":"0","SRP":"1","BoH":-8,"BoH LD":12,"Status":"Art. niedostepny","Zmiana ceny":false,"Price1":39.99,"Price1 LD":39.99,"Loc Price":0,"LocPrice LD":0,"Zmiana lokalizacji":false,"Lokalizacja":"M16N02","LOK LD":"M16N02","FPRICE1":0,"FPRICE LD":0,"Notatki":"Wstaw info \u0027Artykul chwilowo niedostepny\u0027.","EDS":46296,"Fireclass":"NFR","SMDQ":"-"},{"HFB":"15","Product Area":"1521","NR ART.":"00445228","NAZWA ART.":"IVRIG szklanka 45 cl szary 4szt.","SM":"0","SRP":"1","BoH":0,"BoH LD":1,"Status":"Art. niedostepny","Zmiana ceny":false,"Price1":19.99,"Price1 LD":19.99,"Loc Price":0,"LocPrice LD":0,"Zmiana lokalizacji":false,"Lokalizacja":"M15D16","LOK LD":"M15D16","FPRICE1":0,"FPRICE LD":0,"Notatki":"OK.","EDS":46204,"Fireclass":"NFR","SMDQ":"-"},{"HFB":"14","Product Area":"1413","NR ART.":"00464429","NAZWA ART.":"LYCKAD nacz żaro 2s ciemnoszary","SM":"0","SRP":"1","BoH":0,"BoH LD":1,"Status":"Art. niedostepny","Zmiana ceny":false,"Price1":49.99,"Price1 LD":49.99,"Loc Price":0,"LocPrice LD":0,"Zmiana lokalizacji":false,"Lokalizacja":"M14I16","LOK LD":"M14I16","FPRICE1":0,"FPRICE LD":0,"Notatki":"OK.","EDS":"","Fireclass":"NFR","SMDQ":"-"},{"HFB":"01","Product Area":"0125","NR ART.":"00618686","NAZWA ART.":"LILLESÄTER fotel obr AXVALL kremowy","SM":"2","SRP":"1","BoH":0,"BoH LD":4,"Status":"Art. niedostepny","Zmiana ceny":false,"Price1":899,"Price1 LD":899,"Loc Price":0,"LocPrice LD":0,"Zmiana lokalizacji":false,"Lokalizacja":"773500","LOK LD":"773500","FPRICE1":0,"FPRICE LD":0,"Notatki":"OK.","EDS":"","Fireclass":"NFR","SMDQ":"-"},{"HFB":"04","Product Area":"0431","NR ART.":"10458710","NAZWA ART.":"IDANÄS kom 6szu 162x95 biały","SM":"2","SRP":"1","BoH":2,"BoH LD":0,"Status":"Art. dostepny","Zmiana ceny":false,"Price1":1799,"Price1 LD":1799,"Loc Price":0,"LocPrice LD":0,"Zmiana lokalizacji":false,"Lokalizacja":"642900","LOK LD":"642900","FPRICE1":0,"FPRICE LD":0,"Notatki":"Usun info o niedostepnosci artykulu.","EDS":"","Fireclass":"NFR","SMDQ":"-"},{"HFB":"07","Product Area":"0721","NR ART.":"10594982","NAZWA ART.":"LERH pan mask 62x220 niebieski","SM":"2","SRP":"1","BoH":2,"BoH LD":0,"Status":"Art. dostepny","Zmiana ceny":false,"Price1":450,"Price1 LD":450,"Loc Price":0,"LocPrice LD":0,"Zmiana lokalizacji":false,"Lokalizacja":"661510","LOK LD":"661510","FPRICE1":0,"FPRICE LD":0,"Notatki":"Usun info o niedostepnosci artykulu.","EDS":46388,"Fireclass":"NFR","SMDQ":"-"},{"HFB":"16","Product Area":"1644","NR ART.":"10622796","NAZWA ART.":"IKEA PS 2026 ozd śc 3s różowy czerwony/niebieski","SM":"0","SRP":"1","BoH":48,"BoH LD":48,"Status":false,"Zmiana ceny":false,"Price1":29.99,"Price1 LD":29.99,"Loc Price":0,"LocPrice LD":0,"Zmiana lokalizacji":"CO1000","Lokalizacja":"CO1000","LOK LD":0,"FPRICE1":0,"FPRICE LD":0,"Notatki":"OK.","EDS":"","Fireclass":"NFR","SMDQ":"-"},{"HFB":"18","Product Area":"1836","NR ART.":"20504194","NAZWA ART.":"GÖRSNYGG duża torba 57x37x39 cm/71 l jasnobeżowy","SM":"0","SRP":"1","BoH":0,"BoH LD":12,"Status":"Art. niedostepny","Zmiana ceny":false,"Price1":9.99,"Price1 LD":9.99,"Loc Price":0,"LocPrice LD":0,"Zmiana lokalizacji":false,"Lokalizacja":"M18I06","LOK LD":"M18I06","FPRICE1":0,"FPRICE LD":0,"Notatki":"OK.","EDS":"","Fireclass":"NFR","SMDQ":"-"},{"HFB":"16","Product Area":"1622","NR ART.":"20623998","NAZWA ART.":"ROSMARINUS OFFICINALIS NNNNNN r don 14 rozma 14-21","SM":"0","SRP":"1","BoH":-1,"BoH LD":25,"Status":"Art. niedostepny","Zmiana ceny":false,"Price1":19.99,"Price1 LD":19.99,"Loc Price":0,"LocPrice LD":0,"Zmiana lokalizacji":false,"Lokalizacja":"KWIATY","LOK LD":"KWIATY","FPRICE1":0,"FPRICE LD":0,"Notatki":"Wstaw info \u0027Artykul chwilowo niedostepny\u0027.","EDS":46204,"Fireclass":"NFR","SMDQ":"-"},{"HFB":"09","Product Area":"0922","NR ART.":"50526397","NAZWA ART.":"DRÖMSLOTT pud 2s","SM":"0","SRP":"1","BoH":0,"BoH LD":9,"Status":"Art. niedostepny","Zmiana ceny":false,"Price1":39.99,"Price1 LD":39.99,"Loc Price":0,"LocPrice LD":0,"Zmiana lokalizacji":false,"Lokalizacja":"S09P15","LOK LD":"S09P15","FPRICE1":0,"FPRICE LD":0,"Notatki":"OK.","EDS":"","Fireclass":"NFR","SMDQ":"-"},{"HFB":"16","Product Area":"1632","NR ART.":"50612700","NAZWA ART.":"KLOKHET bezzap św stoż 25 cm 6 godz. blnieb 8szt.","SM":"0","SRP":"1","BoH":5,"BoH LD":0,"Status":"Art. dostepny","Zmiana ceny":false,"Price1":14.99,"Price1 LD":14.99,"Loc Price":0,"LocPrice LD":0,"Zmiana lokalizacji":false,"Lokalizacja":"M16O05","LOK LD":"M16O05","FPRICE1":0,"FPRICE LD":0,"Notatki":"Usun info o niedostepnosci artykulu.","EDS":"","Fireclass":"SFR","SMDQ":"-"},{"HFB":"15","Product Area":"1511","NR ART.":"60612894","NAZWA ART.":"SPJUTLILJA talerzyk 20 wzór 4szt.","SM":"0","SRP":"1","BoH":0,"BoH LD":1,"Status":"Art. niedostepny","Zmiana ceny":false,"Price1":29.99,"Price1 LD":29.99,"Loc Price":0,"LocPrice LD":0,"Zmiana lokalizacji":false,"Lokalizacja":"M15D20","LOK LD":"M15D20","FPRICE1":0,"FPRICE LD":0,"Notatki":"OK.","EDS":"","Fireclass":"NFR","SMDQ":"-"},{"HFB":"16","Product Area":"1633","NR ART.":"70618560","NAZWA ART.":"IKEA PS 2026 wazon 15 szkło/biały/zielony różowy","SM":"0","SRP":"1","BoH":270,"BoH LD":270,"Status":false,"Zmiana ceny":false,"Price1":59.99,"Price1 LD":59.99,"Loc Price":0,"LocPrice LD":0,"Zmiana lokalizacji":"CO1000","Lokalizacja":"CO1000","LOK LD":0,"FPRICE1":0,"FPRICE LD":0,"Notatki":"OK.","EDS":"","Fireclass":"NFR","SMDQ":"-"},{"HFB":"10","Product Area":"1024","NR ART.":"80559796","NAZWA ART.":"RODRET bezprz przyciem/przeł smart biały EU","SM":"1","SRP":"7","BoH":-1,"BoH LD":2,"Status":"Art. niedostepny","Zmiana ceny":false,"Price1":29.99,"Price1 LD":29.99,"Loc Price":0,"LocPrice LD":0,"Zmiana lokalizacji":false,"Lokalizacja":"142115","LOK LD":"142115","FPRICE1":0,"FPRICE LD":0,"Notatki":"Wstaw info \u0027Artykul chwilowo niedostepny\u0027.","EDS":46023,"Fireclass":"NFR","SMDQ":"-"},{"HFB":"12","Product Area":"1211","NR ART.":"80614236","NAZWA ART.":"MATILDA N fir 2 145x250 bladoróżowy/na taśmie","SM":"0","SRP":"1","BoH":0,"BoH LD":1,"Status":"Art. niedostepny","Zmiana ceny":false,"Price1":59.99,"Price1 LD":59.99,"Loc Price":0,"LocPrice LD":0,"Zmiana lokalizacji":false,"Lokalizacja":"M12A13","LOK LD":"M12A13","FPRICE1":0,"FPRICE LD":0,"Notatki":"OK.","EDS":"","Fireclass":"NFR","SMDQ":"-"},{"HFB":"18","Product Area":"1821","NR ART.":"90476343","NAZWA ART.":"NEREBY szyna 60 brzoza","SM":"0","SRP":"1","BoH":0,"BoH LD":1,"Status":"Art. niedostepny","Zmiana ceny":false,"Price1":19.99,"Price1 LD":19.99,"Loc Price":0,"LocPrice LD":0,"Zmiana lokalizacji":false,"Lokalizacja":"S07A07","LOK LD":"S07A07","FPRICE1":0,"FPRICE LD":0,"Notatki":"OK.","EDS":46296,"Fireclass":"NFR","SMDQ":"-"},{"HFB":"14","Product Area":"1434","NR ART.":"00618573","NAZWA ART.":"NÅLBLECKA org na blat kuch 23x13x15 metal/bambus","SM":"0","SRP":"1","BoH":0,"BoH LD":13,"Status":"Art. niedostepny","Zmiana ceny":false,"Price1":19.99,"Price1 LD":19.99,"Loc Price":0,"LocPrice LD":0,"Zmiana lokalizacji":false,"Lokalizacja":"M14I16","LOK LD":"M14I16","FPRICE1":0,"FPRICE LD":0,"Notatki":"OK.","EDS":"","Fireclass":"NFR","SMDQ":"-"},{"HFB":"11","Product Area":"1131","NR ART.":"10614391","NAZWA ART.":"GULVIAL ręczniczek 30x30 głęboka czerwień RECY","SM":"0","SRP":"1","BoH":0,"BoH LD":5,"Status":"Art. niedostepny","Zmiana ceny":false,"Price1":7.99,"Price1 LD":7.99,"Loc Price":0,"LocPrice LD":0,"Zmiana lokalizacji":false,"Lokalizacja":"M06P10","LOK LD":"M06P10","FPRICE1":0,"FPRICE LD":0,"Notatki":"OK.","EDS":"","Fireclass":"NFR","SMDQ":"-"},{"HFB":"11","Product Area":"1112","NR ART.":"20575252","NAZWA ART.":"SLÅNHÖSTMAL poszwa/2 poszew 200x200/50x60 cz/b/psk","SM":"0","SRP":"1","BoH":0,"BoH LD":2,"Status":"Art. niedostepny","Zmiana ceny":false,"Price1":129,"Price1 LD":129,"Loc Price":0,"LocPrice LD":0,"Zmiana lokalizacji":false,"Lokalizacja":"M11K15","LOK LD":"M11K15","FPRICE1":0,"FPRICE LD":0,"Notatki":"OK.","EDS":46204,"Fireclass":"NFR","SMDQ":"-"},{"HFB":"12","Product Area":"1232","NR ART.":"20592195","NAZWA ART.":"STOCKHOLM 2025 pled 150x200 jaskrawoniebieski","SM":"0","SRP":"1","BoH":0,"BoH LD":2,"Status":"Art. niedostepny","Zmiana ceny":false,"Price1":249,"Price1 LD":249,"Loc Price":0,"LocPrice LD":0,"Zmiana lokalizacji":false,"Lokalizacja":"M12D13","LOK LD":"M12D13","FPRICE1":0,"FPRICE LD":0,"Notatki":"OK.","EDS":46296,"Fireclass":"NFR","SMDQ":"-"},{"HFB":"07","Product Area":"0721","NR ART.":"40596593","NAZWA ART.":"VALLSTENA pan mask 62x240 biały","SM":"2","SRP":"1","BoH":0,"BoH LD":1,"Status":"Art. niedostepny","Zmiana ceny":false,"Price1":270,"Price1 LD":270,"Loc Price":0,"LocPrice LD":0,"Zmiana lokalizacji":false,"Lokalizacja":"662615","LOK LD":"662615","FPRICE1":0,"FPRICE LD":0,"Notatki":"OK.","EDS":"","Fireclass":"NFR","SMDQ":"-"},{"HFB":"09","Product Area":"0972","NR ART.":"80589350","NAZWA ART.":"LILLABO garaż z samo i helik wielobarwny","SM":"0","SRP":"1","BoH":0,"BoH LD":2,"Status":"Art. niedostepny","Zmiana ceny":false,"Price1":99,"Price1 LD":99,"Loc Price":0,"LocPrice LD":0,"Zmiana lokalizacji":false,"Lokalizacja":"S09U13","LOK LD":"S09U13","FPRICE1":0,"FPRICE LD":0,"Notatki":"OK.","EDS":"","Fireclass":"NFR","SMDQ":"-"},{"HFB":"10","Product Area":"1081","NR ART.":"80615504","NAZWA ART.":"SOLVINDEN 2026 łań św LED, 13 lpk na zewnątrz/wlb","SM":"0","SRP":"1","BoH":0,"BoH LD":1,"Status":"Art. niedostepny","Zmiana ceny":false,"Price1":99.99,"Price1 LD":99.99,"Loc Price":0,"LocPrice LD":0,"Zmiana lokalizacji":false,"Lokalizacja":"M10D09","LOK LD":"M10D09","FPRICE1":0,"FPRICE LD":0,"Notatki":"OK.","EDS":46296,"Fireclass":"NFR","SMDQ":"-"}]}